[{"typeName":"掘金前端","time":"2020-05-29 10:30:19","data":[{"url":"https://juejin.im/post/5ecc0cbef265da770274b2a5","text":"前22年的Loser，后4年和自己赛跑的人 | 最惨前端面经"},{"url":"https://juejin.im/post/5ecf3a9a6fb9a047b75a0a9a","text":"因为一个跨域请求，我差点丢了饭碗"},{"url":"https://juejin.im/post/5ecf58b9f265da76e97d39da","text":"[译]尤雨溪：Vue3的设计过程"},{"url":"https://juejin.im/post/5ecb9872518825432a358b53","text":"聊聊苹果营销页中几个有趣的交互动画"},{"url":"https://juejin.im/post/5ecf022b51882543116e23fb","text":"钉钉前端-如何设计前端实时分析及报警系统"},{"url":"https://juejin.im/post/5ecf38b4e51d45787e43e819","text":"Vue+ Node+mongodb全栈开发王者荣耀手机端官网和管理后台"},{"url":"https://juejin.im/post/5ecb8d77518825433b132ae6","text":"三年前端寒冬入大厂，收获蚂蚁P6+、字节2-1 offer 面经分享"},{"url":"https://juejin.im/post/5ece8637f265da7709525d05","text":"用好这 25 个 VSCode 插件，让开发变得更简单、高效"},{"url":"https://juejin.im/post/5ecf1801518825433e1fa9ab","text":"前端代码是怎样智能生成的？"},{"url":"https://juejin.im/post/5ecd05a1f265da76c4243fe6","text":"Webpack5 上手测评"},{"url":"https://juejin.im/post/5ecf0abc6fb9a047ab2c1720","text":"(已更新 4.1 W字)大前端面试系列之Vue 2.0 核心原理（上）"},{"url":"https://juejin.im/post/5ebb68796fb9a0435432df8e","text":"想自学JS吗？想提升JS底层原理吗？76张脑图带你彻底搞懂原生JS"},{"url":"https://juejin.im/post/5ecdd954e51d45786d3fd8de","text":"《前端那些事》从0到1开发动态表单"},{"url":"https://juejin.im/post/5eca11836fb9a047ff1aa185","text":"带你了解路由的底层原理，用原生js手写一个路由"},{"url":"https://juejin.im/post/5ece4f196fb9a048017052b8","text":"Code Review总结一些Vue开发规范经验"},{"url":"https://juejin.im/post/5ecdd66ff265da76d53c094a","text":"时间切片的实现和调度（原创2.6万字）"},{"url":"https://juejin.im/post/5ece2a1e6fb9a048021466b0","text":"一杯茶的时间，上手 Koa2 + MySQL 开发"},{"url":"https://juejin.im/post/5ecc9b08518825434062fb43","text":"Vue中Axios的封装管理"},{"url":"https://juejin.im/post/5eceaabff265da76e25ca153","text":"ECharts实现可视化全国地图省市县(区)区域下钻"},{"url":"https://juejin.im/post/5ecff3b2f265da76e3277b3a","text":"「中文翻译」Vue3的诞生之路"}]},{"typeName":"NBA资讯","time":"2020-05-29 10:30:17","data":[{"url":"https://xw.qq.com/cmsid/20200529A04FWG00","text":"未来NCAA的中国血液：人家叫他中国锡安 他却想变里海甜瓜\n\n走大蓝GoBigBlue20分钟前"},{"url":"https://xw.qq.com/cmsid/20200529A04F8000","text":"暗讽欧文球商太低！阿里纳斯反驳“球霸论”：我的球商历史前五！\n\n篮板侧沿30分钟前"},{"url":"https://xw.qq.com/cmsid/SPO2020052900096800","text":"没想到你们也有今天！盘点NBA超巨们惨当“背景墙”被隔扣时刻\n\n腾讯体育1小时前"},{"url":"https://xw.qq.com/cmsid/20200529A04LEH00","text":"叫板巴克利！两冠王称今年夺冠更有意义，或为詹皇争历史最佳加分\n\n海青说球28分钟前"},{"url":"https://xw.qq.com/cmsid/20200529A020SX00","text":"名记曝光NBA精心设计复赛规划目的 他们在想方设法为小詹皇“开绿灯”\n\nHCHT59分钟前"},{"url":"https://xw.qq.com/cmsid/20200528A0QSMO00","text":"美媒预测下赛季球员金字塔引争议，莱昂纳德反超詹姆斯成一档太不合理\n\n365天侃篮球24分钟前"},{"url":"https://xw.qq.com/cmsid/SPO2020052900091300","text":"巅峰诺维茨基48分大战杜兰特40分 两大高瘦远投王谁更强？\n\n腾讯体育1小时前"},{"url":"http://view.inews.qq.com/a/VNS202005290012600E","text":"那些从未染指过总冠军的二人组 哪个最可惜？\n\n腾讯体育社区1小时前"},{"url":"https://xw.qq.com/cmsid/20200529A01ONN00","text":"美媒评十大超高性价比年薪！库里1140万排第三，乔丹390万居首\n\n罗说NBA24分钟前"}]}]